MANIFEST.in
README.md
requirements.txt
setup.py
oxford_dic/__init__.py
oxford_dic/__main__.py
oxford_dic.egg-info/PKG-INFO
oxford_dic.egg-info/SOURCES.txt
oxford_dic.egg-info/dependency_links.txt
oxford_dic.egg-info/entry_points.txt
oxford_dic.egg-info/requires.txt
oxford_dic.egg-info/top_level.txt