Metadata-Version: 1.2
Name: oxford-dic
Version: 1.0.1
Summary: CLI interface for Oxford Dictionary
Home-page: https://github.com/miskopo/oxford_dic
Author: Michal Polovka
Author-email: michal.polovka@gmail.com
License: GPL
Platform: linux
Requires-Python: >=3.6
